{"cameraMode":{"drawMode":0,"name":"Shaded","section":"Shading Mode"},"sceneLighting":true,"audioPlay":false,"sceneViewState":{"m_AlwaysRefresh":false,"showFog":true,"showSkybox":true,"showFlares":true,"showImageEffects":true,"showParticleSystems":true,"showVisualEffectGraphs":true,"m_FxEnabled":true},"in2DMode":false,"pivot":{"x":-28.14397621154785,"y":6.972653865814209,"z":-6.678682804107666},"rotation":{"x":-0.0901910811662674,"y":0.6340354681015015,"z":-0.07506847381591797,"w":-0.7644813060760498},"size":11.82749080657959,"orthographic":false}